Metadata-Version: 2.1
Name: django-admin-autocomplete-filter
Version: 0.7.1
Summary: A simple Django app to render list filters in django admin using autocomplete widget
Home-page: https://github.com/farhan0581/django-admin-autocomplete-filter
Author: Farhan Khan
Author-email: farhan0581@gmail.com
License: UNKNOWN
Platform: UNKNOWN
Classifier: Framework :: Django
Classifier: Framework :: Django :: 2.0
Classifier: Intended Audience :: Developers
Classifier: License :: OSI Approved :: GNU Lesser General Public License v3 (LGPLv3)
Classifier: Operating System :: OS Independent
Classifier: Programming Language :: Python :: 3.5
Classifier: Programming Language :: Python :: 3.6
Classifier: Topic :: Internet :: WWW/HTTP
Classifier: Topic :: Software Development :: Libraries :: Python Modules
